{
    "companyName": "SCHNEENET",
    "longName": "WeatherWatch",
    "projectType": "native",
    "resources": {
        "media": [
            {
                "characterRegex": "[0-9:]",
                "file": "fonts/Roboto-Bold.ttf",
                "name": "FONT_ROBOTO_BOLD_SUBSET_39",
                "type": "font"
            },
            {
                "characterRegex": "[0-9:]",
                "file": "fonts/Roboto-Bold.ttf",
                "name": "FONT_ROBOTO_BOLD_SUBSET_49",
                "type": "font"
            },
            {
                "file": "fonts/Roboto-Condensed.ttf",
                "name": "FONT_ROBOTO_CONDENSED_21",
                "type": "font"
            },
			{
				"characterRegex": "[\ue801-\ue82e]",
				"file": "fonts/meteocons.ttf",
				"name": "FONT_METEOCONS_48",
				"type": "font"
			},
            {
                "file": "images/wind.png",
                "name": "WIND",
                "type": "png"
            },
            {
                "file": "images/snow.png",
                "name": "SNOW",
                "type": "png"
            },
            {
                "file": "images/sleet.png",
                "name": "SLEET",
                "type": "png"
            },
            {
                "file": "images/rain.png",
                "name": "RAIN",
                "type": "png"
            },
            {
                "file": "images/partly-cloudy-night.png",
                "name": "PARTLY_CLOUDY_NIGHT",
                "type": "png"
            },
            {
                "file": "images/partly-cloudy-day.png",
                "name": "PARTLY_CLOUDY_DAY",
                "type": "png"
            },
            {
                "file": "images/fog.png",
                "name": "FOG",
                "type": "png"
            },
            {
                "file": "images/error.png",
                "name": "ERROR",
                "type": "png"
            },
            {
                "file": "images/cloudy.png",
                "name": "CLOUDY",
                "type": "png"
            },
            {
                "file": "images/clear-night.png",
                "name": "CLEAR_NIGHT",
                "type": "png"
            },
            {
                "file": "images/clear-day.png",
                "name": "CLEAR_DAY",
                "type": "png"
            }
        ]
    },
    "sdkVersion": "2",
    "shortName": "WeatherWatch",
    "uuid": "455367bd-36cc-4f1d-8002-ff84b2356582",
    "versionCode": 1,
    "versionLabel": "1.0",
    "watchapp": {
        "watchface": true
    }
}
